bitbootpy/__init__.py
bitbootpy/bitbootpy.py
bitbootpy/cli.py
bitbootpy/dht_manager.py
bitbootpy-0.3.0.dist-info/METADATA
bitbootpy-0.3.0.dist-info/WHEEL
bitbootpy-0.3.0.dist-info/RECORD
