Metadata-Version: 2.1
Name: bitbootpy
Version: 0.3.0
Summary: 
Author: estill01
Author-email: ehs.stillman@gmail.com
Requires-Python: >=3.9,<4.0
Classifier: Programming Language :: Python :: 3
Classifier: Programming Language :: Python :: 3.9
Classifier: Programming Language :: Python :: 3.10
Classifier: Programming Language :: Python :: 3.11
Requires-Dist: asyncio (>=3.4.3,<4.0.0)
Requires-Dist: kademlia (>=2.2.2,<3.0.0)
Requires-Dist: tenacity (>=8.2.2,<9.0.0)
Requires-Dist: twisted (>=22.10.0,<23.0.0)
Requires-Dist: uuid (>=1.30,<2.0)
